LICENSE
MANIFEST.in
README.md
requirements.txt
setup.py
pytest_http/__init__.py
pytest_http/plugin.py
pytest_http.egg-info/PKG-INFO
pytest_http.egg-info/SOURCES.txt
pytest_http.egg-info/dependency_links.txt
pytest_http.egg-info/entry_points.txt
pytest_http.egg-info/requires.txt
pytest_http.egg-info/top_level.txt
pytest_http.egg-info/zip-safe
tests/test_pytest_http.py