Metadata-Version: 2.1
Name: pytest-http
Version: 0.1.1
Summary: Fixture "http" for http requests
Home-page: https://github.com/hanzhichao/pytest-http
Author: Han Zhichao
Author-email: superhin@126.com
License: MIT license
Keywords: pytest,py.test,http,requests
Classifier: Framework :: Pytest
Classifier: Programming Language :: Python
Classifier: Topic :: Software Development :: Testing
Classifier: Programming Language :: Python :: 3.7
License-File: LICENSE
Requires-Dist: pytest
Requires-Dist: pytest-runner
Requires-Dist: requests
